Metadata-Version: 1.0
Name: matrix-operations-for-the-basic-people
Version: 0.3
Summary: Basic matrix operations
Home-page: UNKNOWN
Author: Jimmy Lin
Author-email: jimmylinzhe@hotmail.com
License: UNKNOWN
Platform: UNKNOWN
